Lab2/CHORD.vhd
library IEEE;
use IEEE.STD_LOGIC_1164.ALL;
use ieee.NUMERIC_STD.all;
use IEEE.STD_LOGIC_ARITH.ALL;
use IEEE.STD_LOGIC_UNSIGNED.ALL;

entity CHORDEncoder is
    	port(clk, rst: in std_logic;
             a: in std_logic_vector(7 downto 0);
             data_valid: out std_logic;
             z: out std_logic_vector(7 downto 0));
end entity;

architecture behaviour of CHORDEncoder is
  type array_of_vectors is array  (natural range <>) of std_logic_vector(7 downto 0);
  signal buff: array_of_vectors(3 downto 0);
  type IntegerVector is array (natural range <>) of integer;
  --signal buff_int: IntegerVector(3 downto 0);
  signal outputArray: array_of_vectors(32 downto 0);
  signal out_ptr: integer := 0;
  signal buff_ptr: integer := 0;
  signal curr_out: integer := 0;
  signal chord_out: std_logic_vector(7 downto 0);
  signal chord_type: std_logic_vector(7 downto 0);
  signal chord_detected: boolean := false;
  signal keys: array_of_vectors(11 downto 0);
  signal int_keys: IntegerVector(11 downto 0);

  -- Defining type of chords
  signal M: std_logic_vector(7 downto 0):= "01001101";
  signal small_m: std_logic_vector(7 downto 0):= "01101101";
  signal s: std_logic_vector(7 downto 0):= "01110011";
  signal seven: std_logic_vector(7 downto 0):= "00110111";
  signal sharp: std_logic_vector(7 downto 0):= "00011111";
  
  begin
  
  keys(0) <= "01000011";     -- C
  keys(1) <= "01100100";     -- d
  keys(2) <= "01000100";     -- D
  keys(3) <= "01100101";     -- e   
  keys(4) <= "01000101";     -- E
  keys(5) <= "01000110";     -- F
  keys(6) <= "01100111";     -- g
  keys(7) <= "01000111";     -- G
  keys(8) <= "01100001";     -- a
  keys(9) <= "01000001";     -- A
  keys(10) <= "01100010";     -- b
  keys(11) <= "01000010";     -- B

  int_keys(0) <= 01000011;     -- C
  int_keys(1) <= 01100100;     -- d
  int_keys(2) <= 01000100;     -- D
  int_keys(3) <= 01100101;     -- e   
  int_keys(4) <= 01000101;     -- E
  int_keys(5) <= 01000110;     -- F
  int_keys(6) <= 01100111;     -- g
  int_keys(7) <= 01000111;     -- G
  int_keys(8) <= 01100001;     -- a
  int_keys(9) <= 01000001;     -- A
  int_keys(10) <= 01100010;     -- b
  int_keys(11) <= 01000010;     -- B

  process(clk, rst)
    begin
    if rst = '1' then
      buff <= (others => (others => '0'));
      outputArray <= (others => (others => '0'));
      buff_ptr <= 0;
      out_ptr <= 0;
      curr_out <= 0;
      chord_detected <= false;
      data_valid <= '0';
      z <= (others => '0');
    elsif rising_edge(clk) then
      data_valid <= '0';
      report "buff_ptr " &integer'image(buff_ptr) severity note;
      --report "buff(0) " &integer'image() severity note;
      if buff_ptr < 3 then
        --if a /= 00000000 then
          buff(buff_ptr) <= a;
          buff_ptr <= buff_ptr + 1;
        --end if;
      else
       -- buff_int(3) <= to_integer(unsigned(buff(3)));
        report "I am here" severity note;
        if chord_detected = false then
          if ((buff(0) = int_keys(0) and buff(1) = int_keys(4) and buff(2) = int_keys(7) and a = int_keys(10)) or
              (buff(0) = int_keys(1) and buff(1) = int_keys(5) and buff(2) = int_keys(8) and a = int_keys(11)) or
              (buff(0) = int_keys(2) and buff(1) = int_keys(6) and buff(2) = int_keys(9) and a = int_keys(0)) or
              (buff(0) = int_keys(3) and buff(1) = int_keys(7) and buff(2) = int_keys(10) and a = int_keys(1)) or
              (buff(0) = int_keys(4) and buff(1) = int_keys(8) and buff(2) = int_keys(11) and a = int_keys(2)) or
              (buff(0) = int_keys(5) and buff(1) = int_keys(9) and buff(2) = int_keys(0) and a = int_keys(3)) or
              (buff(0) = int_keys(6) and buff(1) = int_keys(10) and buff(2) = int_keys(1) and a = int_keys(4)) or
              (buff(0) = int_keys(7) and buff(1) = int_keys(11) and buff(2) = int_keys(2) and a = int_keys(5)) or
              (buff(0) = int_keys(8) and buff(1) = int_keys(0) and buff(2) = int_keys(3) and a = int_keys(6)) or
              (buff(0) = int_keys(9) and buff(1) = int_keys(1) and buff(2) = int_keys(4) and a = int_keys(7)) or
              (buff(0) = int_keys(10) and buff(1) = int_keys(2) and buff(2) = int_keys(5) and a = int_keys(8)) or
              (buff(0) = int_keys(11) and buff(1) = int_keys(3) and buff(2) = int_keys(6) and a = int_keys(9))
             ) then
            report "Seven" severity note;
            chord_out <= buff(0);
            chord_type <= seven;
            chord_detected <= true;
            
           --elsif ((buff(0) = int_keys(0) and buff(1) = int_keys(4) and buff(2) = int_keys(7)) or
                  --(buff(0) = int_keys(1) and buff(1) = int_keys(5) and buff(2) = int_keys(8)) or
                  --(buff(0) = int_keys(2) and buff(1) = int_keys(6) and buff(2) = int_keys(9)) or
                  --(buff(0) = int_keys(3) and buff(1) = int_keys(7) and buff(2) = int_keys(10)) or
                  --(buff(0) = int_keys(4) and buff(1) = int_keys(8) and buff(2) = int_keys(11)) or
                  --(buff(0) = int_keys(5) and buff(1) = int_keys(9) and buff(2) = int_keys(0)) or
                  --(buff(0) = int_keys(6) and buff(1) = int_keys(10) and buff(2) = int_keys(1)) or
                  --(buff(0) = int_keys(7) and buff(1) = int_keys(11) and buff(2) = int_keys(2)) or
                  --(buff(0) = int_keys(8) and buff(1) = int_keys(0) and buff(2) = int_keys(3)) or
                  --(buff(0) = int_keys(9) and buff(1) = int_keys(1) and buff(2) = int_keys(4)) or
                  --(buff(0) = int_keys(10) and buff(1) = int_keys(2) and buff(2) = int_keys(5)) or
                  --(buff(0) = int_keys(11) and buff(1) = int_keys(3) and buff(2) = int_keys(6))
                 --) then
            elsif (buff(1) - buff(0) = 4) then
             report "Major" severity note;
             chord_out <= buff(0);
             chord_type <= M;
             chord_detected <= true;
             
           elsif ((buff(0) = int_keys(0) and buff(1) = int_keys(3) and buff(2) = int_keys(7)) or
                  (buff(0) = int_keys(1) and buff(1) = int_keys(4) and buff(2) = int_keys(8)) or
                  (buff(0) = int_keys(2) and buff(1) = int_keys(5) and buff(2) = int_keys(9)) or
                  (buff(0) = int_keys(3) and buff(1) = int_keys(6) and buff(2) = int_keys(10)) or
                  (buff(0) = int_keys(4) and buff(1) = int_keys(7) and buff(2) = int_keys(11)) or
                  (buff(0) = int_keys(5) and buff(1) = int_keys(8) and buff(2) = int_keys(0)) or
                  (buff(0) = int_keys(6) and buff(1) = int_keys(9) and buff(2) = int_keys(1)) or
                  (buff(0) = int_keys(7) and buff(1) = int_keys(10) and buff(2) = int_keys(2)) or
                  (buff(0) = int_keys(8) and buff(1) = int_keys(11) and buff(2) = int_keys(3)) or
                  (buff(0) = int_keys(9) and buff(1) = int_keys(0) and buff(2) = int_keys(4)) or
                  (buff(0) = int_keys(10) and buff(1) = int_keys(1) and buff(2) = int_keys(5)) or
                  (buff(0) = int_keys(11) and buff(1) = int_keys(2) and buff(2) = int_keys(6))
                 ) then
             report "Minor" severity note;
             chord_out <= buff(0);
             chord_type <= small_m;
             chord_detected <= true;

           elsif ((buff(0) = int_keys(0) and buff(1) = int_keys(5) and buff(2) = int_keys(7)) or
                  (buff(0) = int_keys(1) and buff(1) = int_keys(6) and buff(2) = int_keys(8)) or
                  (buff(0) = int_keys(2) and buff(1) = int_keys(7) and buff(2) = int_keys(9)) or
                  (buff(0) = int_keys(3) and buff(1) = int_keys(8) and buff(2) = int_keys(10)) or
                  (buff(0) = int_keys(4) and buff(1) = int_keys(9) and buff(2) = int_keys(11)) or
                  (buff(0) = int_keys(5) and buff(1) = int_keys(10) and buff(2) = int_keys(0)) or
                  (buff(0) = int_keys(6) and buff(1) = int_keys(11) and buff(2) = int_keys(1)) or
                  (buff(0) = int_keys(7) and buff(1) = int_keys(0) and buff(2) = int_keys(2)) or
                  (buff(0) = int_keys(8) and buff(1) = int_keys(1) and buff(2) = int_keys(3)) or
                  (buff(0) = int_keys(9) and buff(1) = int_keys(2) and buff(2) = int_keys(4)) or
                  (buff(0) = int_keys(10) and buff(1) = int_keys(3) and buff(2) = int_keys(5)) or
                  (buff(0) = int_keys(11) and buff(1) = int_keys(4) and buff(2) = int_keys(6))
                 ) then
             report "Suspended" severity note;
             chord_out <= buff(0);
             chord_type <= s;
             chord_detected <= true;
           else
             report "NOTHING" severity note;
             outputArray(out_ptr) <= buff(0);
             out_ptr <= out_ptr + 1;
             buff(0) <= buff(1);
             buff(1) <= buff(2);
             buff(2) <= a;
             -- Here error may occur because a may be null.
          end if;   
        end if;

        if chord_detected = true then
          report "Chord Detected" severity note;
          outputArray(out_ptr) <= chord_out;
          out_ptr <= out_ptr + 1;
          outputArray(out_ptr) <= chord_type;
          out_ptr <= out_ptr + 1;
          if chord_type = 00110111 then
            buff <= (others => (others => '0'));
            buff_ptr <= 0;
          else
            buff <= (others => (others => '0'));
            buff(0) <= a;
            buff_ptr <= 1;
          end if;
        end if;

        --OUTPUT Printing:
        data_valid <= '1';
        if out_ptr > 0 then
          z <= outputArray(curr_out);
          curr_out <= curr_out + 1;
        end if;
        report "Curr_out" &integer'image(curr_out) severity note;
        report "Out_ptr " &integer'image(out_ptr) severity note;
      end if;
    end if;
  end process;
end behaviour;

Lab2/22B1844/q3_tb.vhd
library ieee, std;
use ieee.std_logic_1164.all;
use ieee.std_logic_textio.all;
use std.textio.all;

entity ASCII_Read_test is
end entity;

architecture reader of ASCII_Read_test is
	component CHORDEncoder
	    port(clk, rst: in std_logic;
                 a: in std_logic_vector(7 downto 0);
                 data_valid: out std_logic;
                 z: out std_logic_vector(7 downto 0));
	end component;
	signal input_sig, output_sig: std_logic_vector (7 downto 0);
	signal clk, rst, data_valid : std_logic;
begin
	dut_instance: CHORDEncoder
		port map (a => input_sig, clk => clk, z => output_sig, data_valid => data_valid, rst => rst);
	
	process
		file input_file: text open read_mode is "input2.txt";
		file output_file: text open write_mode is "out.txt";
		variable input_line, output_line: line;
		variable input_var, output_var : std_logic_vector (7 downto 0);	
	begin
		while not endfile(input_file) loop
			readline (input_file, input_line);
			read (input_line, input_var);
			input_sig <= input_var;
			wait for 1 ns;
			clk <= '0';
			wait for 1 ns;
			clk <= '1';
			wait for 1 ns;
                end loop;
                while true loop
                  wait for 1 ns;
                  clk <= '1';
                  wait for 1 ns;
                  clk <= '0';
                  output_var := output_sig;
                  write (output_line, output_var);
                  writeline (output_file, output_line);
                  wait for 1 ns;
		end loop;
	wait;
	end process;

end architecture;

Lab2/Q3/ASCII_Read_test.vcd
$date
  Mon Sep 18 21:43:40 2023
$end
$version
  GHDL v0
$end
$timescale
  1 fs
$end
$scope module standard $end
$upscope $end
$scope module std_logic_1164 $end
$upscope $end
$scope module textio $end
$upscope $end
$scope module std_logic_textio $end
$upscope $end
$scope module numeric_std $end
$upscope $end
$scope module ascii_read_test $end
$var reg 8 ! input_sig[7:0] $end
$var reg 8 " output_sig[7:0] $end
$var reg 1 # clk $end
$var reg 1 $ rst $end
$var reg 1 % data_valid $end
$scope module dut_instance $end
$var reg 1 & clk $end
$var reg 1 ' rst $end
$var reg 8 ( a[7:0] $end
$var reg 1 ) data_valid $end
$var reg 8 * z[7:0] $end
$comment buff is not handled $end
$comment outputarray is not handled $end
$var integer 32 + out_ptr $end
$var integer 32 , curr_out $end
$var reg 8 - chord_out[7:0] $end
$var reg 8 . chord_type[7:0] $end
$var reg 1 / chord_detected $end
$comment keys is not handled $end
$comment int_keys is not handled $end
$var reg 8 0 m[7:0] $end
$var reg 8 1 small_m[7:0] $end
$var reg 8 2 s[7:0] $end
$var reg 8 3 seven[7:0] $end
$var reg 8 4 sharp[7:0] $end
$upscope $end
$upscope $end
$enddefinitions $end
#0
b01000011 !
bUUUUUUUU "
U#
U$
U%
U&
U'
b01000011 (
U)
bUUUUUUUU *
b0 +
b0 ,
bUUUUUUUU -
bUUUUUUUU .
0/
b01001101 0
b01101101 1
b01110011 2
b00110111 3
b00011111 4
#1000000
0#
0&
#2000000
1#
1&
#3000000
b01000100 !
b01000100 (
#4000000
0#
0&
#5000000
1#
1&
#6000000
b01000011 !
b01000011 (
#7000000
0#
0&
#8000000
1#
1&
#9000000
b01000101 !
b01000101 (
#10000000
0#
0&
#11000000
1#
1&
b1 +
#12000000
b01000111 !
b01000111 (
#13000000
0#
0&
#14000000
1#
1&
b10 +
#15000000
b01100010 !
b01100010 (
#16000000
0#
0&
#17000000
1#
1&
b01000011 -
b00110111 .
1/
#18000000
b01000100 !
b01000100 (
#19000000
0#
0&
#20000000
1#
1&
b11 +
b00000000 .
0/
#21000000
b01000111 !
b01000111 (
#22000000
0#
0&
#23000000
1#
1&
#24000000
b01000001 !
b01000001 (
#25000000
0#
0&
#26000000
1#
1&
#27000000
#28000000
#29000000
0#
0&
#30000000
#31000000
1#
1&
#32000000
0#
0&
#33000000
#34000000
1#
1&
b100 +
#35000000
0#
0&
#36000000
#37000000
1#
1&
b101 +
#38000000
0#
0&
#39000000
#40000000
1#
1&
b110 +
#41000000
0#
0&
#42000000
#43000000
1#
1&
b111 +
#44000000
0#
0&
#45000000
#46000000
1#
1&
b1000 +
#47000000
0#
0&
#48000000
#49000000
1#
1&
b1001 +
#50000000
0#
0&
#51000000
#52000000
1#
1&
b1010 +
#53000000
0#
0&
#54000000
#55000000
1#
1&
b1011 +
#56000000
0#
0&
#57000000
#58000000
1#
1&
b1100 +
#59000000
0#
0&
#60000000
#61000000
1#
1&
b1101 +
#62000000
0#
0&
#63000000
#64000000
1#
1&
b1110 +
#65000000
0#
0&
#66000000
#67000000
1#
1&
b1111 +
#68000000
0#
0&
#69000000
#70000000
1#
1&
b10000 +
#71000000
0#
0&
#72000000
#73000000
1#
1&
b10001 +
#74000000
0#
0&
#75000000
#76000000
1#
1&
b10010 +
#77000000
0#
0&
#78000000
#79000000
1#
1&
b10011 +
#80000000
0#
0&
#81000000
#82000000
1#
1&
b10100 +
#83000000
0#
0&
#84000000
#85000000
1#
1&
b10101 +
#86000000
0#
0&
#87000000
#88000000
1#
1&
b10110 +
#89000000
0#
0&
#90000000
#91000000
1#
1&
b10111 +
#92000000
0#
0&
#93000000
#94000000
1#
1&
b11000 +
#95000000
0#
0&
#96000000
#97000000
1#
1&
b11001 +
#98000000
0#
0&
#99000000
#100000000
b01000011 "
1#
1%
1&
1)
b01000011 *
b11010 +
b1 ,
#101000000
0#
0&
#102000000
#103000000
b01000100 "
1#
1&
1)
b01000100 *
b11011 +
b10 ,
#104000000
0#
0&
#105000000
#106000000
b00110111 "
1#
1&
1)
b00110111 *
b11100 +
b11 ,
#107000000
0#
0&
#108000000
#109000000
b01000111 "
1#
1&
1)
b01000111 *
b11101 +
b100 ,
#110000000
0#
0&
#111000000
#112000000
b01000001 "
1#
1&
1)
b01000001 *
b11110 +
b101 ,
#113000000
0#
0&
#114000000
#115000000
1#
1&
1)
b11111 +
b110 ,
#116000000
0#
0&
#117000000
#118000000
1#
1&
1)
b100000 +
b111 ,
#119000000
0#
0&
#120000000
#121000000
1#
1&
1)
b100001 +
b1000 ,
