Lab2/22B1844/q2_or.vhd
library IEEE;
use IEEE.std_logic_1164.all;

entity OR_Gate is
    port(x1: in std_logic;
         x2: in std_logic;
         y: out std_logic);
end entity;

architecture behaviour of OR_Gate is

begin
  y <= x1 or x2;

end architecture;

Lab2/22B1844/q1_enc4x2.vhd
library IEEE;
use IEEE.std_logic_1164.all;

entity encoder4x2 is
    port(I: in std_logic_vector (3 downto 0);
         Y: out std_logic_vector(1 downto 0));
end entity;

architecture behaviour of encoder4x2 is

  component OR_Gate is
    port(x1: in std_logic;
         x2: in std_logic;
         y: out std_logic);
  end component;

  begin

  or1: OR_Gate port map(I(3), I(2), Y(1));
  or2: OR_Gate port map(I(3), I(1), Y(0));

  end;

Lab2/22B1844/q1_enc4x2_tb.vhd
library IEEE;
use IEEE.std_logic_1164.all;

entity encoder4x2_tb is
end entity;

architecture tb of encoder4x2_tb is

  component encoder4x2 is
    port(I: in std_logic_vector (3 downto 0);
         Y: out std_logic_vector(1 downto 0));
  end component;

  signal A, B, C, D: std_logic;
  signal Y1, Y0: std_logic;
  
  begin
    dut_instance: encoder4x2
      port map(I(0) => A,
               I(1) => B,
               I(2) => C,
               I(3) => D,
               Y(1) => Y1,
               Y(0) => Y0);

    process
    begin

      A <= '1';
      B <= '0';
      C <= '0';
      D <= '0';

      wait for 1 ns;

      A <= '0';
      B <= '1';
      C <= '0';
      D <= '0';

      wait for 1 ns;

      A <= '0';
      B <= '0';
      C <= '1';
      D <= '0';

      wait for 1 ns;

      A <= '0';
      B <= '0';
      C <= '0';
      D <= '1';

      wait for 1 ns;

      end process;
      
    end architecture;

Lab2/Q1/encoder4x2_tb.vcd
$date
  Thu Sep  7 22:04:44 2023
$end
$version
  GHDL v0
$end
$timescale
  1 fs
$end
$scope module standard $end
$upscope $end
$scope module std_logic_1164 $end
$upscope $end
$scope module encoder4x2_tb $end
$var reg 1 ! a $end
$var reg 1 " b $end
$var reg 1 # c $end
$var reg 1 $ d $end
$var reg 1 % y1 $end
$var reg 1 & y0 $end
$scope module dut_instance $end
$var reg 4 ' i[3:0] $end
$var reg 2 ( y[1:0] $end
$scope module or1 $end
$var reg 1 ) x1 $end
$var reg 1 * x2 $end
$var reg 1 + y $end
$upscope $end
$scope module or2 $end
$var reg 1 , x1 $end
$var reg 1 - x2 $end
$var reg 1 . y $end
$upscope $end
$upscope $end
$upscope $end
$enddefinitions $end
#0
1!
0"
0#
0$
0%
0&
b0001 '
b00 (
0)
0*
0+
0,
0-
0.
#1000000
0!
1"
1&
b0010 '
b01 (
1-
1.
#2000000
0"
1#
1%
0&
b0100 '
b10 (
1*
1+
0-
0.
#3000000
0#
1$
1&
b1000 '
b11 (
1)
0*
1,
1.
#4000000
1!
0$
0%
0&
b0001 '
b00 (
0)
0+
0,
0.
#5000000
0!
1"
1&
b0010 '
b01 (
1-
1.
#6000000
0"
1#
1%
0&
b0100 '
b10 (
1*
1+
0-
0.
#7000000
0#
1$
1&
b1000 '
b11 (
1)
0*
1,
1.
#8000000
1!
0$
0%
0&
b0001 '
b00 (
0)
0+
0,
0.
