Lab2/22B1844/q2_not.vhd
library IEEE;
use IEEE.std_logic_1164.all;

entity NOT_Gate is
    port(x: in std_logic;
         y: out std_logic);
end entity;

architecture behaviour of NOT_Gate is

begin
  y <= not x;

end architecture;

Lab2/22B1844/q1_not_tb.vhd
library IEEE;
use IEEE.std_logic_1164.all;

entity not_tb is
end entity;

architecture tb of not_tb is

  signal i: std_logic;
  signal g: std_logic;

  component NOT_Gate is
    port(x: in std_logic;
         y: out std_logic);
  end component;

begin
  dut_instance: NOT_Gate
  port map(x => i, y => g);

  process
  begin

    i <= '0';

    wait for 1 ns;

    i <= '1';

    wait for 1 ns;

    end process;

end architecture;

Lab2/Q1/not_tb.vcd
$date
  Thu Sep  7 22:03:23 2023
$end
$version
  GHDL v0
$end
$timescale
  1 fs
$end
$scope module standard $end
$upscope $end
$scope module std_logic_1164 $end
$upscope $end
$scope module not_tb $end
$var reg 1 ! i $end
$var reg 1 " g $end
$scope module dut_instance $end
$var reg 1 # x $end
$var reg 1 $ y $end
$upscope $end
$upscope $end
$enddefinitions $end
#0
0!
1"
0#
1$
#1000000
1!
0"
1#
0$
#2000000
0!
1"
0#
1$
#3000000
1!
0"
1#
0$
#4000000
0!
1"
0#
1$
#5000000
1!
0"
1#
0$
#6000000
0!
1"
0#
1$
#7000000
1!
0"
1#
0$
#8000000
0!
1"
0#
1$
