Lab2/22B1844/q2_or.vhd
library IEEE;
use IEEE.std_logic_1164.all;

entity OR_Gate is
    port(x1: in std_logic;
         x2: in std_logic;
         y: out std_logic);
end entity;

architecture behaviour of OR_Gate is

begin
  y <= x1 or x2;

end architecture;

Lab2/22B1844/q1_or_tb.vhd
library IEEE;
use IEEE.std_logic_1164.all;

entity or_tb is
end entity;

architecture tb of or_tb is

  signal i1, i2: std_logic;
  signal g: std_logic;

  component OR_Gate is
    port(x1: in std_logic;
         x2: in std_logic;
         y: out std_logic);
  end component;

begin
  dut_instance: OR_Gate
  port map(x1 => i1, x2 => i2, y => g);

  process
  begin

    i1 <= '0';
    i2 <= '0';

    wait for 1 ns;

    i1 <= '0';
    i2 <= '1';

    wait for 1 ns;

    i1 <= '1';
    i2 <= '0';

    wait for 1 ns;

    i1 <= '1';
    i2 <= '1';

    wait for 1 ns;

    end process;

end architecture;

Lab2/Q1/or_tb.vcd
$date
  Thu Sep  7 22:02:27 2023
$end
$version
  GHDL v0
$end
$timescale
  1 fs
$end
$scope module standard $end
$upscope $end
$scope module std_logic_1164 $end
$upscope $end
$scope module or_tb $end
$var reg 1 ! i1 $end
$var reg 1 " i2 $end
$var reg 1 # g $end
$scope module dut_instance $end
$var reg 1 $ x1 $end
$var reg 1 % x2 $end
$var reg 1 & y $end
$upscope $end
$upscope $end
$enddefinitions $end
#0
0!
0"
0#
0$
0%
0&
#1000000
1"
1#
1%
1&
#2000000
1!
0"
1$
0%
#3000000
1"
1%
#4000000
0!
0"
0#
0$
0%
0&
#5000000
1"
1#
1%
1&
#6000000
1!
0"
1$
0%
#7000000
1"
1%
#8000000
0!
0"
0#
0$
0%
0&
