Lab2/22B1844/q1_and.vhd
library IEEE;
use IEEE.std_logic_1164.all;

entity AND_Gate is
  port(x1: in std_logic;
       x2: in std_logic;
       y: out std_logic);
end entity;

architecture behaviour of AND_Gate is

begin
  y <= x1 and x2;

end architecture;

Lab2/22B1844/q2_not.vhd
library IEEE;
use IEEE.std_logic_1164.all;

entity NOT_Gate is
    port(x: in std_logic;
         y: out std_logic);
end entity;

architecture behaviour of NOT_Gate is

begin
  y <= not x;

end architecture;

Lab2/22B1844/q2_decoder2x4.vhd
library IEEE;
use IEEE.std_logic_1164.all;

entity decoder2x4 is
    port(D1, D0: in std_logic;
         enable: in std_logic;
         Y: out std_logic_vector (3 downto 0));
end entity;

architecture behaviour of decoder2x4 is

  component AND_Gate is
    port(x1: in std_logic;
         x2: in std_logic;
         y: out std_logic);
  end component;

  component NOT_Gate is
    port(x: in std_logic;
         y: out std_logic);
  end component;

  signal not_D1, not_D0: std_logic;
  signal temp0, temp1, temp2, temp3: std_logic;
  begin

  not1: NOT_Gate port map(D1, not_D1);
  not2: NOT_Gate port map(D0, not_D0);
  and0: AND_Gate port map(not_D1, not_D0, temp0);
  and_0: AND_Gate port map(temp0, enable, Y(0));
  and1: AND_Gate port map(not_D1, D0, temp1);
  and_1: AND_Gate port map(temp1, enable, Y(1));
  and2: AND_Gate port map(D1, not_D0, temp2);
  and_2: AND_Gate port map(temp2, enable, Y(2));
  and3: AND_Gate port map(D1, D0, temp3);
  and_3: AND_Gate port map(temp3, enable, Y(3));

  end;

Lab2/22B1844/q2_decoder2x4_tb.vhd
library IEEE;
use IEEE.std_logic_1164.all;

entity decoder2x4_tb is
end entity;

architecture tb of decoder2x4_tb is

  component decoder2x4 is
    port(D1, D0: in std_logic;
         enable: in std_logic;
         Y: out std_logic_vector (3 downto 0));
  end component;

  signal A, B, E: std_logic;
  signal Y0, Y1, Y2, Y3: std_logic;

  begin
    dut_instance: decoder2x4
      port map(D0 => A,
               D1 => B,
               Y(0) => Y0,
               Y(1) => Y1,
               Y(2) => Y2,
               Y(3) => Y3,
               enable => E);
    process
    begin

      E <= '1';  -- enable
      
      A <= '1';
      B <= '0';

      wait for 1 ns;

      A <= '0';
      B <= '1';

      wait for 1 ns;

      A <= '1';
      B <= '1';

      wait for 1 ns;

      A <= '0';
      B <= '0';

      wait for 1 ns;

      E <= '0';   -- enable
      
      A <= '0';
      B <= '0';

      wait for 1 ns;

      A <= '1';
      B <= '0';

      wait for 1 ns;

      A <= '0';
      B <= '1';

      wait for 1 ns;

      A <= '1';
      B <= '1';

      wait for 1 ns;

      E <= '1';  -- enable
      
      A <= '1';
      B <= '1';

      wait for 1 ns;

      A <= '1';
      B <= '0';

      wait for 1 ns;

      A <= '0';
      B <= '0';

      wait for 1 ns;

      A <= '0';
      B <= '1';

      wait for 1 ns;

      E <= '0';  -- enable
      
      A <= '0';
      B <= '1';

      wait for 1 ns;

      A <= '1';
      B <= '1';

      wait for 1 ns;

      A <= '0';
      B <= '0';

      wait for 1 ns;

      A <= '1';
      B <= '0';

      wait for 1 ns;

      end process;

    end architecture;

Lab2/Q2/decoder2x4_tb.vcd
$date
  Thu Sep  7 23:34:05 2023
$end
$version
  GHDL v0
$end
$timescale
  1 fs
$end
$scope module standard $end
$upscope $end
$scope module std_logic_1164 $end
$upscope $end
$scope module decoder2x4_tb $end
$var reg 1 ! a $end
$var reg 1 " b $end
$var reg 1 # e $end
$var reg 1 $ y0 $end
$var reg 1 % y1 $end
$var reg 1 & y2 $end
$var reg 1 ' y3 $end
$scope module dut_instance $end
$var reg 1 ( d1 $end
$var reg 1 ) d0 $end
$var reg 1 * enable $end
$var reg 4 + y[3:0] $end
$var reg 1 , not_d1 $end
$var reg 1 - not_d0 $end
$var reg 1 . temp0 $end
$var reg 1 / temp1 $end
$var reg 1 0 temp2 $end
$var reg 1 1 temp3 $end
$scope module not1 $end
$var reg 1 2 x $end
$var reg 1 3 y $end
$upscope $end
$scope module not2 $end
$var reg 1 4 x $end
$var reg 1 5 y $end
$upscope $end
$scope module and0 $end
$var reg 1 6 x1 $end
$var reg 1 7 x2 $end
$var reg 1 8 y $end
$upscope $end
$scope module and_0 $end
$var reg 1 9 x1 $end
$var reg 1 : x2 $end
$var reg 1 ; y $end
$upscope $end
$scope module and1 $end
$var reg 1 < x1 $end
$var reg 1 = x2 $end
$var reg 1 > y $end
$upscope $end
$scope module and_1 $end
$var reg 1 ? x1 $end
$var reg 1 @ x2 $end
$var reg 1 A y $end
$upscope $end
$scope module and2 $end
$var reg 1 B x1 $end
$var reg 1 C x2 $end
$var reg 1 D y $end
$upscope $end
$scope module and_2 $end
$var reg 1 E x1 $end
$var reg 1 F x2 $end
$var reg 1 G y $end
$upscope $end
$scope module and3 $end
$var reg 1 H x1 $end
$var reg 1 I x2 $end
$var reg 1 J y $end
$upscope $end
$scope module and_3 $end
$var reg 1 K x1 $end
$var reg 1 L x2 $end
$var reg 1 M y $end
$upscope $end
$upscope $end
$upscope $end
$enddefinitions $end
#0
1!
0"
1#
0$
1%
0&
0'
0(
1)
1*
b0010 +
1,
0-
0.
1/
00
01
02
13
14
05
16
07
08
09
1:
0;
1<
1=
1>
1?
1@
1A
0B
0C
0D
0E
1F
0G
0H
1I
0J
0K
1L
0M
#1000000
0!
1"
0%
1&
1(
0)
b0100 +
0,
1-
0/
10
12
03
04
15
06
17
0<
0=
0>
0?
0A
1B
1C
1D
1E
1G
1H
0I
#2000000
1!
0&
1'
1)
b1000 +
0-
00
11
14
05
07
1=
0C
0D
0E
0G
1I
1J
1K
1M
#3000000
0!
0"
1$
0'
0(
0)
b0001 +
1,
1-
1.
01
02
13
04
15
16
17
18
19
1;
1<
0=
0B
1C
0H
0I
0J
0K
0M
#4000000
0#
0$
0*
b0000 +
0:
0;
0@
0F
0L
#5000000
1!
1)
0-
0.
1/
14
05
07
08
09
1=
1>
1?
0C
1I
#6000000
0!
1"
1(
0)
0,
1-
0/
10
12
03
04
15
06
17
0<
0=
0>
0?
1B
1C
1D
1E
1H
0I
#7000000
1!
1)
0-
00
11
14
05
07
1=
0C
0D
0E
1I
1J
1K
#8000000
1#
1'
1*
b1000 +
1:
1@
1F
1L
1M
#9000000
0"
1%
0'
0(
b0010 +
1,
1/
01
02
13
16
1<
1>
1?
1A
0B
0H
0J
0K
0M
#10000000
0!
1$
0%
0)
b0001 +
1-
1.
0/
04
15
17
18
19
1;
0=
0>
0?
0A
1C
0I
#11000000
1"
0$
1&
1(
b0100 +
0,
0.
10
12
03
06
08
09
0;
0<
1B
1D
1E
1G
1H
#12000000
0#
0&
0*
b0000 +
0:
0@
0F
0G
0L
#13000000
1!
1)
0-
00
11
14
05
07
1=
0C
0D
0E
1I
1J
1K
#14000000
0!
0"
0(
0)
1,
1-
1.
01
02
13
04
15
16
17
18
19
1<
0=
0B
1C
0H
0I
0J
0K
#15000000
1!
1)
0-
0.
1/
14
05
07
08
09
1=
1>
1?
0C
1I
#16000000
1#
1%
1*
b0010 +
1:
1@
1A
1F
1L
